murmurhash2-0.2.10.dist-info/METADATA
murmurhash2-0.2.10.dist-info/WHEEL
murmurhash2/__init__.py
murmurhash2/__init__.pyi
murmurhash2/py.typed
murmurhash2/murmurhash2.abi3.so
murmurhash2-0.2.10.dist-info/RECORD
