Metadata-Version: 2.1
Name: murmurhash2
Version: 0.2.10
Summary: murmurhash2 for Python
Author: messense <messense@icloud.com>
Author-email: messense <messense@icloud.com>
License: MIT
Project-URL: Source Code, https://github.com/messense/murmurhash2-py
